{
	"lines":[
		{
			"portrait":"weirded",
			"text":"It could be... a statue made by Flesh to Stone?"
		},
		{
			"portrait":"laughing",
			"text":"Like maybe the stone in question is some sort of blue crystal, and..."
		},
		{"action":"fade","in":false},
		{
			"portrait":"blank",
			"text":"You walk over and touch the hologram."
		},
		{
			"portrait":"blank",
			"text":"Or, more accurately, you walk over and don't."
		},
		{
			"portrait":"exhausted",
			"text":"Nuts. Not a statue."
		},
		{"action":"fade","in":true},
		{
			"portrait":"pensive",
			"text":"Could be a <c=#FF00FF>different Stop spell,</c> though..."
		},
        {
			"action":"hypothesis"
		}
	]
}